examples/example_single_rec.py
examples/import_data_example.py
examples/visualize_h5_data.py
opyndata/__init__.py
opyndata/data_import.py
opyndata/misc.py
opyndata/visualization.py
opyndata-0.0.3.dist-info/METADATA
opyndata-0.0.3.dist-info/WHEEL
opyndata-0.0.3.dist-info/top_level.txt
opyndata-0.0.3.dist-info/RECORD
