Metadata-Version: 2.2
Name: opyndata
Version: 0.0.3
Summary: OpyNDATA toolbox for import and postprocessing of measurement data
Author-email: "Knut A. Kvåle" <knut.a.kvale@ntnu.no>
Project-URL: repository, https://github.com/knutankv/opyndata
Project-URL: documentation, https://knutankv.github.io/opyndata/
Classifier: License :: OSI Approved :: MIT License
Classifier: Operating System :: OS Independent
Classifier: Programming Language :: Python :: 3
Classifier: Topic :: Scientific/Engineering
Requires-Python: >=3.6
Requires-Dist: numpy
Requires-Dist: scipy
Requires-Dist: pandas
Requires-Dist: matplotlib
Requires-Dist: h5py
Requires-Dist: dash
Requires-Dist: plotly
Requires-Dist: datetime
Requires-Dist: flask
